lognition/__init__.py
lognition/logger.py
lognition/main.py
lognition-0.0.13.dist-info/LICENSE
lognition-0.0.13.dist-info/METADATA
lognition-0.0.13.dist-info/WHEEL
lognition-0.0.13.dist-info/top_level.txt
lognition-0.0.13.dist-info/RECORD
