Metadata-Version: 2.2
Name: lognition
Version: 0.0.13
Summary: Log everything in style.
Author: Abtin Turing
Classifier: Programming Language :: Python :: 3
Classifier: License :: OSI Approved :: MIT License
Classifier: Operating System :: OS Independent
License-File: LICENSE
Requires-Dist: coloredlogs
Requires-Dist: verboselogs
Requires-Dist: yaspin
Dynamic: author
Dynamic: classifier
Dynamic: description
Dynamic: description-content-type
Dynamic: requires-dist
Dynamic: summary
